eolic/__init__.py
eolic/base.py
eolic/helpers/__init__.py
eolic/helpers/coroutines.py
eolic/helpers/modules.py
eolic/integrations/__init__.py
eolic/integrations/base.py
eolic/integrations/celery.py
eolic/integrations/fastapi.py
eolic/listener.py
eolic/meta/__init__.py
eolic/meta/singleton.py
eolic/model.py
eolic/remote.py
eolic/task_manager.py
eolic-0.2.0.dist-info/LICENSE
eolic-0.2.0.dist-info/METADATA
eolic-0.2.0.dist-info/WHEEL
eolic-0.2.0.dist-info/RECORD
