Metadata-Version: 2.1
Name: eolic
Version: 0.2.0
Summary: 
Home-page: https://github.com/thiarthur/eolic
License: MIT
Author: Thiago Goslar
Author-email: thiarthur1@gmail.com
Requires-Python: >=3.9,<4.0
Classifier: License :: OSI Approved :: MIT License
Classifier: Programming Language :: Python :: 3
Classifier: Programming Language :: Python :: 3.9
Classifier: Programming Language :: Python :: 3.10
Classifier: Programming Language :: Python :: 3.11
Classifier: Programming Language :: Python :: 3.12
Provides-Extra: all
Provides-Extra: celery
Provides-Extra: fastapi
Requires-Dist: celery ; extra == "celery" or extra == "all"
Requires-Dist: fastapi ; extra == "fastapi" or extra == "all"
Requires-Dist: pydantic (>=2.8.2,<3.0.0)
Requires-Dist: requests (>=2.32.3,<3.0.0)
Requires-Dist: uvicorn ; extra == "fastapi" or extra == "all"
Project-URL: Documentation, https://github.com/thiarthur/eolic/tree/master/docs
Project-URL: Repository, https://github.com/thiarthur/eolic
